[
  {
    "id": 1780291974417,
    "createdAt": 1780291974139,
    "equipment": "Printer",
    "title": "Printer Maintenance",
    "inspectionDate": "2026-03-06",
    "scheduledDate": "2026-03-06",
    "reference": "ITDF-01",
    "frequency": "Quarterly",
    "period": "Q1",
    "brand": "",
    "model": "",
    "serial": "",
    "description": "Cleaning and resetting ink pad\nRemarks: Units is working and tested",
    "inspectedBy": "Joseph Diala",
    "checkedBy": "",
    "status": "completed",
    "asset": "Printer",
    "checks": {
      "checkParts": false,
      "cleanInteriors": false,
      "operatingCondition": false,
      "electricalWires": false
    }
  },
  {
    "id": 1780291974418,
    "createdAt": 1780291974139,
    "equipment": "Epson L5290",
    "title": "Epson L5290 Maintenance",
    "inspectionDate": "2026-04-15",
    "scheduledDate": "2026-04-15",
    "reference": "ITDF-01",
    "frequency": "Quarterly",
    "period": "Q2",
    "brand": "",
    "model": "",
    "serial": "",
    "description": "The printer\\'s wasted ink is leaking from the ink absorber, the printer needs to be replaced and maintained.\nRemarks: Units is working and tested good",
    "inspectedBy": "Joseph Diala",
    "checkedBy": "",
    "status": "completed",
    "asset": "Epson L5290",
    "checks": {
      "checkParts": false,
      "cleanInteriors": false,
      "operatingCondition": false,
      "electricalWires": false
    }
  },
  {
    "id": 1780291974419,
    "createdAt": 1780291974139,
    "equipment": "Epson L6270",
    "title": "Epson L6270 Maintenance",
    "inspectionDate": "2026-04-20",
    "scheduledDate": "2026-04-20",
    "reference": "ITDF-01",
    "frequency": "Quarterly",
    "period": "Q2",
    "brand": "",
    "model": "",
    "serial": "",
    "description": "I checked the printout and also inspected the printer\\'s interior to see if there were any scattered inks on the printer\\'s chassis. So far it\\'s ok, the only problem I see is that its maintenance box is almost full.\nRemarks: Replace for maintenance box",
    "inspectedBy": "Joseph Diala / John Richard",
    "checkedBy": "",
    "status": "completed",
    "asset": "Epson L6270",
    "checks": {
      "checkParts": false,
      "cleanInteriors": false,
      "operatingCondition": false,
      "electricalWires": false
    }
  },
  {
    "id": 1780291974420,
    "createdAt": 1780291974139,
    "equipment": "Sharp Copier",
    "title": "Sharp Copier Maintenance",
    "inspectionDate": "2026-05-28",
    "scheduledDate": "2026-05-28",
    "reference": "ITDF-01",
    "frequency": "Quarterly",
    "period": "Q2",
    "brand": "",
    "model": "",
    "serial": "",
    "description": "Check why the copier always misfeeds in tray 1.\nRemarks: Replace Paper feed roller, separate roller and pickup roller",
    "inspectedBy": "Joseph Diala",
    "checkedBy": "",
    "status": "completed",
    "asset": "Sharp Copier",
    "checks": {
      "checkParts": false,
      "cleanInteriors": false,
      "operatingCondition": false,
      "electricalWires": false
    }
  },
  {
    "id": 1780291974421,
    "createdAt": 1780291974139,
    "equipment": "Sharp Copier BP-30M28",
    "title": "Sharp Copier BP-30M28 Inspection",
    "inspectionDate": "2026-05-04",
    "scheduledDate": "2026-05-04",
    "reference": "ITDF-01",
    "frequency": "Weekly",
    "period": "Week 1",
    "brand": "Sharp Copier",
    "model": "BP-30M28",
    "serial": 4501822100,
    "description": "Unit is Working and no problem found",
    "inspectedBy": "Joseph Diala",
    "checkedBy": "IT",
    "status": "completed",
    "asset": "Sharp Copier BP-30M28",
    "checks": {
      "checkParts": false,
      "cleanInteriors": true,
      "operatingCondition": true,
      "electricalWires": false
    }
  },
  {
    "id": 1780291974422,
    "createdAt": 1780291974139,
    "equipment": "Sharp Copier BP-30M28",
    "title": "Sharp Copier BP-30M28 Inspection",
    "inspectionDate": "2026-05-04",
    "scheduledDate": "2026-05-04",
    "reference": "ITDF-01",
    "frequency": "Weekly",
    "period": "Week 1",
    "brand": "Sharp Copier",
    "model": "BP-30M28",
    "serial": 5592782100,
    "description": "Unit is Working and no problem found",
    "inspectedBy": "Joseph Diala",
    "checkedBy": "IT",
    "status": "completed",
    "asset": "Sharp Copier BP-30M28",
    "checks": {
      "checkParts": false,
      "cleanInteriors": true,
      "operatingCondition": true,
      "electricalWires": false
    }
  },
  {
    "id": 1780291974423,
    "createdAt": 1780291974139,
    "equipment": "Sharp Copier BP-30M28",
    "title": "Sharp Copier BP-30M28 Inspection",
    "inspectionDate": "2026-05-04",
    "scheduledDate": "2026-05-04",
    "reference": "ITDF-01",
    "frequency": "Weekly",
    "period": "Week 1",
    "brand": "Sharp Copier",
    "model": "BP-30M28",
    "serial": 4501821100,
    "description": "Unit is Working and no problem found",
    "inspectedBy": "Joseph Diala",
    "checkedBy": "IT",
    "status": "completed",
    "asset": "Sharp Copier BP-30M28",
    "checks": {
      "checkParts": false,
      "cleanInteriors": true,
      "operatingCondition": true,
      "electricalWires": false
    }
  },
  {
    "id": 1780291974424,
    "createdAt": 1780291974139,
    "equipment": "Epson L6270",
    "title": "Epson L6270 Inspection",
    "inspectionDate": "2026-05-04",
    "scheduledDate": "2026-05-04",
    "reference": "ITDF-01",
    "frequency": "Weekly",
    "period": "Week 1",
    "brand": "Epson",
    "model": "Epson L6270",
    "serial": "",
    "description": "Unit is Working and tested good",
    "inspectedBy": "Joseph Diala",
    "checkedBy": "IT",
    "status": "completed",
    "asset": "Epson L6270",
    "checks": {
      "checkParts": false,
      "cleanInteriors": true,
      "operatingCondition": true,
      "electricalWires": false
    }
  },
  {
    "id": 1780291974425,
    "createdAt": 1780291974139,
    "equipment": "Epson L5290",
    "title": "Epson L5290 Inspection",
    "inspectionDate": "2026-05-04",
    "scheduledDate": "2026-05-04",
    "reference": "ITDF-01",
    "frequency": "Weekly",
    "period": "Week 1",
    "brand": "Epson",
    "model": "Epson L5290",
    "serial": "X8H5122643",
    "description": "Unit is working and tested good",
    "inspectedBy": "Joseph Diala",
    "checkedBy": "IT",
    "status": "completed",
    "asset": "Epson L5290",
    "checks": {
      "checkParts": false,
      "cleanInteriors": true,
      "operatingCondition": true,
      "electricalWires": false
    }
  },
  {
    "id": 1780291974426,
    "createdAt": 1780291974139,
    "equipment": "Epson L5290",
    "title": "Epson L5290 Inspection",
    "inspectionDate": "2026-05-04",
    "scheduledDate": "2026-05-04",
    "reference": "ITDF-01",
    "frequency": "Weekly",
    "period": "Week 1",
    "brand": "Epson",
    "model": "Epson L5290",
    "serial": "X8H5230040",
    "description": "Unit is working and Tested Good",
    "inspectedBy": "Joseph Diala",
    "checkedBy": "IT",
    "status": "completed",
    "asset": "Epson L5290",
    "checks": {
      "checkParts": false,
      "cleanInteriors": true,
      "operatingCondition": true,
      "electricalWires": false
    }
  },
  {
    "id": 1780291974427,
    "createdAt": 1780291974139,
    "equipment": "Sharp Copier BP-30M28",
    "title": "Sharp Copier BP-30M28 Inspection",
    "inspectionDate": "2026-05-11",
    "scheduledDate": "2026-05-11",
    "reference": "ITDF-01",
    "frequency": "Weekly",
    "period": "Week 2",
    "brand": "Sharp Copier",
    "model": "BP-30M28",
    "serial": 4501822100,
    "description": "Unit is Working and no problem found",
    "inspectedBy": "Joseph Diala",
    "checkedBy": "IT",
    "status": "completed",
    "asset": "Sharp Copier BP-30M28",
    "checks": {
      "checkParts": false,
      "cleanInteriors": true,
      "operatingCondition": true,
      "electricalWires": false
    }
  },
  {
    "id": 1780291974428,
    "createdAt": 1780291974139,
    "equipment": "Sharp Copier BP-30M28",
    "title": "Sharp Copier BP-30M28 Inspection",
    "inspectionDate": "2026-05-11",
    "scheduledDate": "2026-05-11",
    "reference": "ITDF-01",
    "frequency": "Weekly",
    "period": "Week 2",
    "brand": "Sharp Copier",
    "model": "BP-30M28",
    "serial": 5592782100,
    "description": "Unit is Working and no problem found",
    "inspectedBy": "Joseph Diala",
    "checkedBy": "IT",
    "status": "completed",
    "asset": "Sharp Copier BP-30M28",
    "checks": {
      "checkParts": false,
      "cleanInteriors": true,
      "operatingCondition": true,
      "electricalWires": false
    }
  },
  {
    "id": 1780291974429,
    "createdAt": 1780291974139,
    "equipment": "Sharp Copier BP-30M28",
    "title": "Sharp Copier BP-30M28 Inspection",
    "inspectionDate": "2026-05-11",
    "scheduledDate": "2026-05-11",
    "reference": "ITDF-01",
    "frequency": "Weekly",
    "period": "Week 2",
    "brand": "Sharp Copier",
    "model": "BP-30M28",
    "serial": 4501821100,
    "description": "Unit is Working and no problem found",
    "inspectedBy": "Joseph Diala",
    "checkedBy": "IT",
    "status": "completed",
    "asset": "Sharp Copier BP-30M28",
    "checks": {
      "checkParts": false,
      "cleanInteriors": true,
      "operatingCondition": true,
      "electricalWires": false
    }
  },
  {
    "id": 1780291974430,
    "createdAt": 1780291974139,
    "equipment": "Epson L6270",
    "title": "Epson L6270 Inspection",
    "inspectionDate": "2026-05-11",
    "scheduledDate": "2026-05-11",
    "reference": "ITDF-01",
    "frequency": "Weekly",
    "period": "Week 2",
    "brand": "Epson",
    "model": "Epson L6270",
    "serial": "",
    "description": "Unit is Working and tested good",
    "inspectedBy": "Joseph Diala",
    "checkedBy": "IT",
    "status": "completed",
    "asset": "Epson L6270",
    "checks": {
      "checkParts": false,
      "cleanInteriors": true,
      "operatingCondition": true,
      "electricalWires": false
    }
  },
  {
    "id": 1780291974431,
    "createdAt": 1780291974139,
    "equipment": "Epson L5290",
    "title": "Epson L5290 Inspection",
    "inspectionDate": "2026-05-11",
    "scheduledDate": "2026-05-11",
    "reference": "ITDF-01",
    "frequency": "Weekly",
    "period": "Week 2",
    "brand": "Epson",
    "model": "Epson L5290",
    "serial": "X8H5122643",
    "description": "Unit is working and tested good",
    "inspectedBy": "Joseph Diala",
    "checkedBy": "IT",
    "status": "completed",
    "asset": "Epson L5290",
    "checks": {
      "checkParts": false,
      "cleanInteriors": true,
      "operatingCondition": true,
      "electricalWires": false
    }
  },
  {
    "id": 1780291974432,
    "createdAt": 1780291974139,
    "equipment": "Epson L5290",
    "title": "Epson L5290 Inspection",
    "inspectionDate": "2026-05-11",
    "scheduledDate": "2026-05-11",
    "reference": "ITDF-01",
    "frequency": "Weekly",
    "period": "Week 2",
    "brand": "Epson",
    "model": "Epson L5290",
    "serial": "X8H5230040",
    "description": "refilled black ink tank. Unit is working and Tested Good",
    "inspectedBy": "Joseph Diala",
    "checkedBy": "IT",
    "status": "completed",
    "asset": "Epson L5290",
    "checks": {
      "checkParts": false,
      "cleanInteriors": true,
      "operatingCondition": true,
      "electricalWires": false
    }
  },
  {
    "id": 1780291974433,
    "createdAt": 1780291974139,
    "equipment": "HP Smart Tank 515",
    "title": "HP Smart Tank 515 Inspection",
    "inspectionDate": "2026-03-06",
    "scheduledDate": "2026-03-06",
    "reference": "ITDF-01",
    "frequency": "Quarterly",
    "period": "Q1",
    "brand": "HP",
    "model": "Smart Tank 515",
    "serial": "CN32J4406N",
    "description": "I checked the interior, operating condition, the wiring and the printer parts and consumables. So far the printer is still ok and working.",
    "inspectedBy": "Joseph Diala",
    "checkedBy": "IT",
    "status": "completed",
    "asset": "HP Smart Tank 515",
    "checks": {
      "checkParts": true,
      "cleanInteriors": true,
      "operatingCondition": true,
      "electricalWires": true
    }
  },
  {
    "id": 1780291974434,
    "createdAt": 1780291974139,
    "equipment": "Epson L805",
    "title": "Epson L805 Inspection",
    "inspectionDate": "2026-03-06",
    "scheduledDate": "2026-03-06",
    "reference": "ITDF-01",
    "frequency": "Quarterly",
    "period": "Q1",
    "brand": "Epson",
    "model": "Epson L805",
    "serial": "W85K644846",
    "description": "I checked the interior, operating condition, the wiring and the printer parts and consumables. So far the printer is still ok and working.",
    "inspectedBy": "Joseph Diala",
    "checkedBy": "IT",
    "status": "completed",
    "asset": "Epson L805",
    "checks": {
      "checkParts": true,
      "cleanInteriors": true,
      "operatingCondition": true,
      "electricalWires": true
    }
  },
  {
    "id": 1780291974435,
    "createdAt": 1780291974139,
    "equipment": "Epson L8050",
    "title": "Epson L8050 Inspection",
    "inspectionDate": "2026-03-06",
    "scheduledDate": "2026-03-06",
    "reference": "ITDF-01",
    "frequency": "Quarterly",
    "period": "Q1",
    "brand": "Epson",
    "model": "Epson L8050",
    "serial": "XB54010356",
    "description": "I checked the interior, operating condition, the wiring and the printer parts and consumables. So far the printer is still ok and working.",
    "inspectedBy": "Joseph Diala",
    "checkedBy": "IT",
    "status": "completed",
    "asset": "Epson L8050",
    "checks": {
      "checkParts": true,
      "cleanInteriors": true,
      "operatingCondition": true,
      "electricalWires": true
    }
  },
  {
    "id": 1780291974436,
    "createdAt": 1780291974139,
    "equipment": "Epson L5290",
    "title": "Epson L5290 Inspection",
    "inspectionDate": "2026-03-06",
    "scheduledDate": "2026-03-06",
    "reference": "ITDF-01",
    "frequency": "Quarterly",
    "period": "Q1",
    "brand": "Epson",
    "model": "Epson L5290",
    "serial": "XH85167809",
    "description": "I checked the interior, operating condition, the wiring and the printer parts and consumables. So far the printer is still ok and working.",
    "inspectedBy": "Joseph Diala",
    "checkedBy": "IT",
    "status": "completed",
    "asset": "Epson L5290",
    "checks": {
      "checkParts": true,
      "cleanInteriors": true,
      "operatingCondition": true,
      "electricalWires": true
    }
  },
  {
    "id": 1780291974437,
    "createdAt": 1780291974139,
    "equipment": "Epson L5290",
    "title": "Epson L5290 Inspection",
    "inspectionDate": "2026-03-06",
    "scheduledDate": "2026-03-06",
    "reference": "ITDF-01",
    "frequency": "Quarterly",
    "period": "Q1",
    "brand": "Epson",
    "model": "Epson L5290",
    "serial": "X8H5129791",
    "description": "I checked the interior, operating condition, the wiring and the printer parts and consumables. So far the printer is still ok and working.",
    "inspectedBy": "Joseph Diala",
    "checkedBy": "IT",
    "status": "completed",
    "asset": "Epson L5290",
    "checks": {
      "checkParts": true,
      "cleanInteriors": true,
      "operatingCondition": true,
      "electricalWires": true
    }
  },
  {
    "id": 1780291974438,
    "createdAt": 1780291974139,
    "equipment": "Epson L5290",
    "title": "Epson L5290 Inspection",
    "inspectionDate": "2026-03-06",
    "scheduledDate": "2026-03-06",
    "reference": "ITDF-01",
    "frequency": "Quarterly",
    "period": "Q1",
    "brand": "Epson",
    "model": "Epson L5290",
    "serial": "X8H5083574",
    "description": "I checked the interior, operating condition, the wiring and the printer parts and consumables. So far the printer is still ok and working.",
    "inspectedBy": "Joseph Diala",
    "checkedBy": "IT",
    "status": "completed",
    "asset": "Epson L5290",
    "checks": {
      "checkParts": true,
      "cleanInteriors": true,
      "operatingCondition": true,
      "electricalWires": true
    }
  },
  {
    "id": 1780291974439,
    "createdAt": 1780291974139,
    "equipment": "Epson L5290",
    "title": "Epson L5290 Inspection",
    "inspectionDate": "2026-03-06",
    "scheduledDate": "2026-03-06",
    "reference": "ITDF-01",
    "frequency": "Quarterly",
    "period": "Q1",
    "brand": "Epson",
    "model": "Epson L5290",
    "serial": "X8H5083551",
    "description": "I checked the interior, operating condition, the wiring and the printer parts and consumables. So far the printer is still ok and working.",
    "inspectedBy": "Joseph Diala",
    "checkedBy": "IT",
    "status": "completed",
    "asset": "Epson L5290",
    "checks": {
      "checkParts": true,
      "cleanInteriors": true,
      "operatingCondition": true,
      "electricalWires": true
    }
  },
  {
    "id": 1780291974440,
    "createdAt": 1780291974139,
    "equipment": "Epson L5290",
    "title": "Epson L5290 Inspection",
    "inspectionDate": "2026-03-06",
    "scheduledDate": "2026-03-06",
    "reference": "ITDF-01",
    "frequency": "Quarterly",
    "period": "Q1",
    "brand": "Epson",
    "model": "Epson L5290",
    "serial": "X8H5230040",
    "description": "I checked the interior, operating condition, the wiring and the printer parts and consumables. So far the printer is still ok and working.",
    "inspectedBy": "Joseph Diala",
    "checkedBy": "IT",
    "status": "completed",
    "asset": "Epson L5290",
    "checks": {
      "checkParts": true,
      "cleanInteriors": true,
      "operatingCondition": true,
      "electricalWires": true
    }
  },
  {
    "id": 1780291974441,
    "createdAt": 1780291974139,
    "equipment": "Brother DCP T-300",
    "title": "Brother DCP T-300 Inspection",
    "inspectionDate": "2026-03-06",
    "scheduledDate": "2026-03-06",
    "reference": "ITDF-01",
    "frequency": "Quarterly",
    "period": "Q1",
    "brand": "Brother",
    "model": "DCP T-300",
    "serial": "E74706H6H757850",
    "description": "I checked the interior, operating condition, the wiring and the printer parts and consumables. So far the printer is still ok and working.",
    "inspectedBy": "Joseph Diala",
    "checkedBy": "IT",
    "status": "completed",
    "asset": "Brother DCP T-300",
    "checks": {
      "checkParts": true,
      "cleanInteriors": true,
      "operatingCondition": true,
      "electricalWires": true
    }
  },
  {
    "id": 1780291974442,
    "createdAt": 1780291974139,
    "equipment": "Epson L5290",
    "title": "Epson L5290 Inspection",
    "inspectionDate": "2026-03-06",
    "scheduledDate": "2026-03-06",
    "reference": "ITDF-01",
    "frequency": "Quarterly",
    "period": "Q1",
    "brand": "Epson",
    "model": "Epson L5290",
    "serial": "X8H5122643",
    "description": "I checked the interior, operating condition, the wiring and the printer parts and consumables. So far the printer is still ok and working.",
    "inspectedBy": "Joseph Diala",
    "checkedBy": "IT",
    "status": "completed",
    "asset": "Epson L5290",
    "checks": {
      "checkParts": true,
      "cleanInteriors": true,
      "operatingCondition": true,
      "electricalWires": true
    }
  },
  {
    "id": 1780291974443,
    "createdAt": 1780291974139,
    "equipment": "Epson L5290",
    "title": "Epson L5290 Inspection",
    "inspectionDate": "2026-03-06",
    "scheduledDate": "2026-03-06",
    "reference": "ITDF-01",
    "frequency": "Quarterly",
    "period": "Q1",
    "brand": "Epson",
    "model": "Epson L5290",
    "serial": "X8H5122643",
    "description": "I checked the interior, operating condition, the wiring and the printer parts and consumables. So far the printer is still ok and working.",
    "inspectedBy": "Joseph Diala",
    "checkedBy": "IT",
    "status": "completed",
    "asset": "Epson L5290",
    "checks": {
      "checkParts": true,
      "cleanInteriors": true,
      "operatingCondition": true,
      "electricalWires": true
    }
  },
  {
    "id": 1780291974444,
    "createdAt": 1780291974139,
    "equipment": "Sharp Copier BP-30M28",
    "title": "Sharp Copier BP-30M28 Inspection",
    "inspectionDate": "2026-03-06",
    "scheduledDate": "2026-03-06",
    "reference": "ITDF-01",
    "frequency": "Quarterly",
    "period": "Q1",
    "brand": "Sharp Copier",
    "model": "BP-30M28",
    "serial": 4501821100,
    "description": "I checked the interior, operating condition, the wiring and the printer parts and consumables. So far the printer is still ok and working.",
    "inspectedBy": "Joseph Diala",
    "checkedBy": "IT",
    "status": "completed",
    "asset": "Sharp Copier BP-30M28",
    "checks": {
      "checkParts": true,
      "cleanInteriors": true,
      "operatingCondition": true,
      "electricalWires": true
    }
  },
  {
    "id": 1780291974445,
    "createdAt": 1780291974139,
    "equipment": "Epson L3250",
    "title": "Epson L3250 Inspection",
    "inspectionDate": "2026-03-06",
    "scheduledDate": "2026-03-06",
    "reference": "ITDF-01",
    "frequency": "Quarterly",
    "period": "Q1",
    "brand": "Epson",
    "model": "Epson L3250",
    "serial": "X94H010686",
    "description": "I checked the interior, operating condition, the wiring and the printer parts and consumables. So far the printer is still ok and working.",
    "inspectedBy": "Joseph Diala",
    "checkedBy": "IT",
    "status": "completed",
    "asset": "Epson L3250",
    "checks": {
      "checkParts": true,
      "cleanInteriors": true,
      "operatingCondition": true,
      "electricalWires": true
    }
  },
  {
    "id": 1780291974446,
    "createdAt": 1780291974139,
    "equipment": "Sharp Copier BP-30M28",
    "title": "Sharp Copier BP-30M28 Inspection",
    "inspectionDate": "2026-03-06",
    "scheduledDate": "2026-03-06",
    "reference": "ITDF-01",
    "frequency": "Quarterly",
    "period": "Q1",
    "brand": "Sharp Copier",
    "model": "BP-30M28",
    "serial": 5592782100,
    "description": "I checked the interior, operating condition, the wiring and the printer parts and consumables. So far the printer is still ok and working.",
    "inspectedBy": "Joseph Diala",
    "checkedBy": "IT",
    "status": "completed",
    "asset": "Sharp Copier BP-30M28",
    "checks": {
      "checkParts": true,
      "cleanInteriors": true,
      "operatingCondition": true,
      "electricalWires": true
    }
  },
  {
    "id": 1780291974447,
    "createdAt": 1780291974139,
    "equipment": "Epson L5290",
    "title": "Epson L5290 Inspection",
    "inspectionDate": "2026-03-06",
    "scheduledDate": "2026-03-06",
    "reference": "ITDF-01",
    "frequency": "Quarterly",
    "period": "Q1",
    "brand": "Epson",
    "model": "Epson L5290",
    "serial": "X8JZM22272",
    "description": "I checked the interior, operating condition, the wiring and the printer parts and consumables. So far the printer is still ok and working.",
    "inspectedBy": "Joseph Diala",
    "checkedBy": "IT",
    "status": "completed",
    "asset": "Epson L5290",
    "checks": {
      "checkParts": true,
      "cleanInteriors": true,
      "operatingCondition": true,
      "electricalWires": true
    }
  },
  {
    "id": 1780291974448,
    "createdAt": 1780291974139,
    "equipment": "Sharp Copier BP-30M28",
    "title": "Sharp Copier BP-30M28 Inspection",
    "inspectionDate": "2026-03-06",
    "scheduledDate": "2026-03-06",
    "reference": "ITDF-01",
    "frequency": "Quarterly",
    "period": "Q1",
    "brand": "Sharp Copier",
    "model": "BP-30M28",
    "serial": 4501822100,
    "description": "I checked the interior, operating condition, the wiring and the printer parts and consumables. So far the printer is still ok and working.",
    "inspectedBy": "Joseph Diala",
    "checkedBy": "IT",
    "status": "completed",
    "asset": "Sharp Copier BP-30M28",
    "checks": {
      "checkParts": true,
      "cleanInteriors": true,
      "operatingCondition": true,
      "electricalWires": true
    }
  },
  {
    "id": 1780291974449,
    "createdAt": 1780291974139,
    "equipment": "Epson LX-310",
    "title": "Epson LX-310 Inspection",
    "inspectionDate": "2026-03-09",
    "scheduledDate": "2026-03-09",
    "reference": "ITDF-01",
    "frequency": "Quarterly",
    "period": "Q1",
    "brand": "Epson",
    "model": "LX-310",
    "serial": "Q7CYJ46181",
    "description": "I checked the interior, operating condition, the wiring and the printer parts and consumables. So far the printer is still ok and working.",
    "inspectedBy": "Joseph Diala",
    "checkedBy": "IT",
    "status": "completed",
    "asset": "Epson LX-310",
    "checks": {
      "checkParts": true,
      "cleanInteriors": true,
      "operatingCondition": true,
      "electricalWires": true
    }
  },
  {
    "id": 1780291974450,
    "createdAt": 1780291974139,
    "equipment": "Epson LX-310",
    "title": "Epson LX-310 Inspection",
    "inspectionDate": "2026-03-09",
    "scheduledDate": "2026-03-09",
    "reference": "ITDF-01",
    "frequency": "Quarterly",
    "period": "Q1",
    "brand": "Epson",
    "model": "LX-310",
    "serial": "Q7CY793508",
    "description": "I checked the interior, operating condition, the wiring and the printer parts and consumables. So far the printer is still ok and working.",
    "inspectedBy": "Joseph Diala",
    "checkedBy": "IT",
    "status": "completed",
    "asset": "Epson LX-310",
    "checks": {
      "checkParts": true,
      "cleanInteriors": true,
      "operatingCondition": true,
      "electricalWires": true
    }
  },
  {
    "id": 1780291974451,
    "createdAt": 1780291974139,
    "equipment": "Epson LX-310",
    "title": "Epson LX-310 Inspection",
    "inspectionDate": "2026-03-09",
    "scheduledDate": "2026-03-09",
    "reference": "ITDF-01",
    "frequency": "Quarterly",
    "period": "Q1",
    "brand": "Epson",
    "model": "LX-310",
    "serial": "QICYJ22360",
    "description": "I checked the interior, operating condition, the wiring and the printer parts and consumables. So far the printer is still ok and working.",
    "inspectedBy": "Joseph Diala",
    "checkedBy": "IT",
    "status": "completed",
    "asset": "Epson LX-310",
    "checks": {
      "checkParts": true,
      "cleanInteriors": true,
      "operatingCondition": true,
      "electricalWires": true
    }
  },
  {
    "id": 1780291974452,
    "createdAt": 1780291974139,
    "equipment": "Epson LX-310",
    "title": "Epson LX-310 Inspection",
    "inspectionDate": "2026-03-09",
    "scheduledDate": "2026-03-09",
    "reference": "ITDF-01",
    "frequency": "Quarterly",
    "period": "Q1",
    "brand": "Epson",
    "model": "LX-310",
    "serial": "Q7CYJ22201",
    "description": "I checked the interior, operating condition, the wiring and the printer parts and consumables. So far the printer is still ok and working.",
    "inspectedBy": "Joseph Diala",
    "checkedBy": "IT",
    "status": "completed",
    "asset": "Epson LX-310",
    "checks": {
      "checkParts": true,
      "cleanInteriors": true,
      "operatingCondition": true,
      "electricalWires": true
    }
  },
  {
    "id": 1780291974453,
    "createdAt": 1780291974139,
    "equipment": "Epson LX-310",
    "title": "Epson LX-310 Inspection",
    "inspectionDate": "2026-03-09",
    "scheduledDate": "2026-03-09",
    "reference": "ITDF-01",
    "frequency": "Quarterly",
    "period": "Q1",
    "brand": "Epson",
    "model": "LX-310",
    "serial": "Q7CYJ43421",
    "description": "I checked the interior, operating condition, the wiring and the printer parts and consumables. So far the printer is still ok and working.",
    "inspectedBy": "Joseph Diala",
    "checkedBy": "IT",
    "status": "completed",
    "asset": "Epson LX-310",
    "checks": {
      "checkParts": true,
      "cleanInteriors": true,
      "operatingCondition": true,
      "electricalWires": true
    }
  },
  {
    "id": 1780291974454,
    "createdAt": 1780291974139,
    "equipment": "Epson LX-310",
    "title": "Epson LX-310 Inspection",
    "inspectionDate": "2026-03-09",
    "scheduledDate": "2026-03-09",
    "reference": "ITDF-01",
    "frequency": "Quarterly",
    "period": "Q1",
    "brand": "Epson",
    "model": "LX-310",
    "serial": "Q7CYJ47414",
    "description": "I checked the interior, operating condition, the wiring and the printer parts and consumables. So far the printer is still ok and working.",
    "inspectedBy": "Joseph Diala",
    "checkedBy": "IT",
    "status": "completed",
    "asset": "Epson LX-310",
    "checks": {
      "checkParts": true,
      "cleanInteriors": true,
      "operatingCondition": true,
      "electricalWires": true
    }
  },
  {
    "id": 1780291974455,
    "createdAt": 1780291974139,
    "equipment": "Epson LX-310",
    "title": "Epson LX-310 Inspection",
    "inspectionDate": "2026-03-09",
    "scheduledDate": "2026-03-09",
    "reference": "ITDF-01",
    "frequency": "Quarterly",
    "period": "Q1",
    "brand": "Epson",
    "model": "LX-310",
    "serial": "Q7CY138347",
    "description": "I checked the interior, operating condition, the wiring and the printer parts and consumables. So far the printer is still ok and working.",
    "inspectedBy": "Joseph Diala",
    "checkedBy": "IT",
    "status": "completed",
    "asset": "Epson LX-310",
    "checks": {
      "checkParts": true,
      "cleanInteriors": true,
      "operatingCondition": true,
      "electricalWires": true
    }
  },
  {
    "id": 1780291974456,
    "createdAt": 1780291974139,
    "equipment": "Epson LX-310",
    "title": "Epson LX-310 Inspection",
    "inspectionDate": "2026-03-09",
    "scheduledDate": "2026-03-09",
    "reference": "ITDF-01",
    "frequency": "Quarterly",
    "period": "Q1",
    "brand": "Epson",
    "model": "LX-310",
    "serial": "Q7CYJ095684",
    "description": "I checked the interior, operating condition, the wiring and the printer parts and consumables. So far the printer is still ok and working.",
    "inspectedBy": "Joseph Diala",
    "checkedBy": "IT",
    "status": "completed",
    "asset": "Epson LX-310",
    "checks": {
      "checkParts": true,
      "cleanInteriors": true,
      "operatingCondition": true,
      "electricalWires": true
    }
  },
  {
    "id": 1780291974457,
    "createdAt": 1780291974139,
    "equipment": "Sharp Copier BP-30M28",
    "title": "Sharp Copier BP-30M28 Inspection",
    "inspectionDate": "2026-05-18",
    "scheduledDate": "2026-05-18",
    "reference": "ITDF-01",
    "frequency": "Weekly",
    "period": "Week 3",
    "brand": "Sharp Copier",
    "model": "BP-30M28",
    "serial": 4501822100,
    "description": "There is no problem with the machine, it works as intended.",
    "inspectedBy": "Joseph S. Diala",
    "checkedBy": "IT",
    "status": "completed",
    "asset": "Sharp Copier BP-30M28",
    "checks": {
      "checkParts": false,
      "cleanInteriors": true,
      "operatingCondition": true,
      "electricalWires": true
    }
  },
  {
    "id": 1780291974458,
    "createdAt": 1780291974139,
    "equipment": "Sharp Copier BP-30M28",
    "title": "Sharp Copier BP-30M28 Inspection",
    "inspectionDate": "2026-05-18",
    "scheduledDate": "2026-05-18",
    "reference": "ITDF-01",
    "frequency": "Weekly",
    "period": "Week 3",
    "brand": "Sharp Copier",
    "model": "BP-30M28",
    "serial": 5592782100,
    "description": "There is no problem with the machine, it works as intended.",
    "inspectedBy": "Joseph S. Diala",
    "checkedBy": "IT",
    "status": "completed",
    "asset": "Sharp Copier BP-30M28",
    "checks": {
      "checkParts": false,
      "cleanInteriors": true,
      "operatingCondition": true,
      "electricalWires": false
    }
  },
  {
    "id": 1780291974459,
    "createdAt": 1780291974139,
    "equipment": "Sharp Copier BP-30M28",
    "title": "Sharp Copier BP-30M28 Inspection",
    "inspectionDate": "2026-05-18",
    "scheduledDate": "2026-05-18",
    "reference": "ITDF-01",
    "frequency": "Weekly",
    "period": "Week 3",
    "brand": "Sharp Copier",
    "model": "BP-30M28",
    "serial": 4501821100,
    "description": "There is no problem with the machine, it works as intended.",
    "inspectedBy": "Joseph S. Diala",
    "checkedBy": "IT",
    "status": "completed",
    "asset": "Sharp Copier BP-30M28",
    "checks": {
      "checkParts": false,
      "cleanInteriors": true,
      "operatingCondition": true,
      "electricalWires": true
    }
  },
  {
    "id": 1780291974460,
    "createdAt": 1780291974139,
    "equipment": "Epson L6270",
    "title": "Epson L6270 Inspection",
    "inspectionDate": "2026-05-18",
    "scheduledDate": "2026-05-18",
    "reference": "ITDF-01",
    "frequency": "Weekly",
    "period": "Week 3",
    "brand": "Epson",
    "model": "L6270",
    "serial": "",
    "description": "There is no problem with the machine, it works as intended.",
    "inspectedBy": "Joseph S. Diala",
    "checkedBy": "IT",
    "status": "completed",
    "asset": "Epson L6270",
    "checks": {
      "checkParts": false,
      "cleanInteriors": true,
      "operatingCondition": true,
      "electricalWires": true
    }
  },
  {
    "id": 1780291974461,
    "createdAt": 1780291974139,
    "equipment": "Epson L5290",
    "title": "Epson L5290 Inspection",
    "inspectionDate": "2026-05-18",
    "scheduledDate": "2026-05-18",
    "reference": "ITDF-01",
    "frequency": "Weekly",
    "period": "Week 3",
    "brand": "Epson",
    "model": "L5290",
    "serial": "X8H5230040",
    "description": "There is no problem with the machine, it works as intended.",
    "inspectedBy": "Joseph S. Diala",
    "checkedBy": "IT",
    "status": "completed",
    "asset": "Epson L5290",
    "checks": {
      "checkParts": false,
      "cleanInteriors": true,
      "operatingCondition": true,
      "electricalWires": true
    }
  },
  {
    "id": 1780291974462,
    "createdAt": 1780291974139,
    "equipment": "Epson L5290",
    "title": "Epson L5290 Inspection",
    "inspectionDate": "2026-05-18",
    "scheduledDate": "2026-05-18",
    "reference": "ITDF-01",
    "frequency": "Weekly",
    "period": "Week 3",
    "brand": "Epson",
    "model": "L5290",
    "serial": "X8H5122643",
    "description": "There is no problem with the machine, it works as intended.",
    "inspectedBy": "Joseph S. Diala",
    "checkedBy": "IT",
    "status": "completed",
    "asset": "Epson L5290",
    "checks": {
      "checkParts": false,
      "cleanInteriors": true,
      "operatingCondition": true,
      "electricalWires": true
    }
  },
  {
    "id": 1780291974463,
    "createdAt": 1780291974139,
    "equipment": "Sharp Copier BP-30M28",
    "title": "Sharp Copier BP-30M28 Inspection",
    "inspectionDate": "2026-05-25",
    "scheduledDate": "2026-05-25",
    "reference": "ITDF-01",
    "frequency": "Weekly",
    "period": "Week 4",
    "brand": "Sharp Copier",
    "model": "BP-30M28",
    "serial": 5592782100,
    "description": "Based on my observations, the unit is working and I haven\\'t encountered any problems.",
    "inspectedBy": "Joseph S. Diala",
    "checkedBy": "IT",
    "status": "completed",
    "asset": "Sharp Copier BP-30M28",
    "checks": {
      "checkParts": false,
      "cleanInteriors": true,
      "operatingCondition": true,
      "electricalWires": false
    }
  },
  {
    "id": 1780291974464,
    "createdAt": 1780291974139,
    "equipment": "Sharp Copier BP-30M28",
    "title": "Sharp Copier BP-30M28 Inspection",
    "inspectionDate": "2026-05-25",
    "scheduledDate": "2026-05-25",
    "reference": "ITDF-01",
    "frequency": "Weekly",
    "period": "Week 4",
    "brand": "Sharp Copier",
    "model": "BP-30M28",
    "serial": 4501822100,
    "description": "Based on my observations, the unit is working and I haven\\'t encountered any problems.",
    "inspectedBy": "Joseph S. Diala",
    "checkedBy": "IT",
    "status": "completed",
    "asset": "Sharp Copier BP-30M28",
    "checks": {
      "checkParts": false,
      "cleanInteriors": true,
      "operatingCondition": true,
      "electricalWires": false
    }
  },
  {
    "id": 1780291974465,
    "createdAt": 1780291974139,
    "equipment": "Sharp Copier BP-30M28",
    "title": "Sharp Copier BP-30M28 Inspection",
    "inspectionDate": "2026-05-25",
    "scheduledDate": "2026-05-25",
    "reference": "ITDF-01",
    "frequency": "Weekly",
    "period": "Week 4",
    "brand": "Sharp Copier",
    "model": "BP-30M28",
    "serial": 4501821100,
    "description": "Based on my observations, the unit is working and I haven\\'t encountered any problems.",
    "inspectedBy": "Joseph S. Diala",
    "checkedBy": "IT",
    "status": "completed",
    "asset": "Sharp Copier BP-30M28",
    "checks": {
      "checkParts": false,
      "cleanInteriors": true,
      "operatingCondition": true,
      "electricalWires": false
    }
  },
  {
    "id": 1780291974466,
    "createdAt": 1780291974139,
    "equipment": "Epson L6270",
    "title": "Epson L6270 Inspection",
    "inspectionDate": "2026-05-25",
    "scheduledDate": "2026-05-25",
    "reference": "ITDF-01",
    "frequency": "Weekly",
    "period": "Week 4",
    "brand": "Epson",
    "model": "L6270",
    "serial": "X8FN023450",
    "description": "Based on my observations, the unit is working and I haven\\'t encountered any problems.",
    "inspectedBy": "Joseph S. Diala",
    "checkedBy": "IT",
    "status": "completed",
    "asset": "Epson L6270",
    "checks": {
      "checkParts": false,
      "cleanInteriors": true,
      "operatingCondition": true,
      "electricalWires": false
    }
  },
  {
    "id": 1780291974467,
    "createdAt": 1780291974139,
    "equipment": "Epson L5290",
    "title": "Epson L5290 Inspection",
    "inspectionDate": "2026-05-25",
    "scheduledDate": "2026-05-25",
    "reference": "ITDF-01",
    "frequency": "Weekly",
    "period": "Week 4",
    "brand": "Epson",
    "model": "L5290",
    "serial": "X8H5230040",
    "description": "Based on my observations, the unit is working and I haven\\'t encountered any problems.",
    "inspectedBy": "Joseph S. Diala",
    "checkedBy": "IT",
    "status": "completed",
    "asset": "Epson L5290",
    "checks": {
      "checkParts": false,
      "cleanInteriors": true,
      "operatingCondition": true,
      "electricalWires": false
    }
  },
  {
    "id": 1780291974468,
    "createdAt": 1780291974139,
    "equipment": "Epson L5290",
    "title": "Epson L5290 Inspection",
    "inspectionDate": "2026-05-25",
    "scheduledDate": "2026-05-25",
    "reference": "ITDF-01",
    "frequency": "Weekly",
    "period": "Week 4",
    "brand": "Epson",
    "model": "L5290",
    "serial": "X8H5230040",
    "description": "Based on my observation, the unit is working but the printer head has a problem, the yellow ink is not coming out properly. The printer will work if it is all black and less use of the color yellow.",
    "inspectedBy": "Joseph S. Diala",
    "checkedBy": "IT",
    "status": "completed",
    "asset": "Epson L5290",
    "checks": {
      "checkParts": false,
      "cleanInteriors": true,
      "operatingCondition": true,
      "electricalWires": false
    }
  }
]